{
  "timestamp": "2026-05-15T15:00:00Z",
  "total_posts": 20,
  "posts": [
    {
      "id": "P001",
      "source_type": "citizen",
      "platform": "Twitter",
      "username": "@karachiwala92",
      "text": "Surjani Town mein pani aa gaya yaar! Sector 11 ki sadak band ho gayi. Rescue walo ko bulao jaldi!",
      "location": "Surjani Town",
      "coordinates": {"lat": 24.9801, "lng": 67.0359},
      "timestamp": "2026-05-15T14:20:00Z",
      "credibility": 62,
      "likes": 145,
      "retweets": 89,
      "verified": false
    },
    {
      "id": "P002",
      "source_type": "news_outlet",
      "platform": "Geo News",
      "username": "@GeoNewsUrdu",
      "text": "BREAKING: Surjani Town flooding emergency — 45mm rain in 2 hours. DMC teams dispatched. Residents urged to evacuate ground floors.",
      "location": "Surjani Town",
      "coordinates": {"lat": 24.9815, "lng": 67.0342},
      "timestamp": "2026-05-15T14:45:00Z",
      "credibility": 94,
      "likes": 3200,
      "retweets": 1800,
      "verified": true
    },
    {
      "id": "P003",
      "source_type": "citizen",
      "platform": "Facebook",
      "username": "Ahmed Baloch",
      "text": "North Karachi mein aaj bohat zyada garmi hai. Mere ghar ke 2 bacha behosh ho gaye. Hospital le gaye hain. Kohi water dispense karo please sector 11.",
      "location": "North Karachi",
      "coordinates": {"lat": 24.9924, "lng": 67.0637},
      "timestamp": "2026-05-15T15:00:00Z",
      "credibility": 58,
      "likes": 432,
      "retweets": 0,
      "verified": false
    },
    {
      "id": "P004",
      "source_type": "verified",
      "platform": "Twitter",
      "username": "@DMCKarachi",
      "text": "District Municipal Corporation Alert: Urban flooding confirmed in Surjani Town Sectors 11-A, 11-B, 11-C. Emergency response activated. Helpline: 1122",
      "location": "Surjani Town",
      "coordinates": {"lat": 24.9801, "lng": 67.0359},
      "timestamp": "2026-05-15T14:50:00Z",
      "credibility": 96,
      "likes": 890,
      "retweets": 2100,
      "verified": true
    },
    {
      "id": "P005",
      "source_type": "field_team",
      "platform": "CIRO Field App",
      "username": "FT-Karachi-North-01",
      "text": "Field assessment complete: Surjani flooding depth 1.5ft on main road, 0.8ft in residential alleys. 3 elderly residents stranded. Rescue needed at House 45-B, Sector 11-C.",
      "location": "Surjani Town",
      "coordinates": {"lat": 24.9810, "lng": 67.0355},
      "timestamp": "2026-05-15T15:05:00Z",
      "credibility": 98,
      "likes": 0,
      "retweets": 0,
      "verified": true
    },
    {
      "id": "P006",
      "source_type": "citizen",
      "platform": "WhatsApp (shared)",
      "username": "Unknown",
      "text": "Surjani mein koi flood nahi hai. Bas normal barish hai. Log drama kar rahe hain. Main abhi wahan se aa raha hun.",
      "location": "Surjani Town",
      "coordinates": {"lat": 24.9801, "lng": 67.0359},
      "timestamp": "2026-05-15T14:55:00Z",
      "credibility": 22,
      "likes": 0,
      "retweets": 0,
      "verified": false,
      "flag": "contradicts_verified_reports"
    },
    {
      "id": "P007",
      "source_type": "news_outlet",
      "platform": "ARY News",
      "username": "@ARYNewsUrdu",
      "text": "North Karachi heatwave: Temperature reaches 43C. Edhi Foundation distributing water in Sector 14. 8 heat exhaustion cases in last hour.",
      "location": "North Karachi",
      "coordinates": {"lat": 24.9924, "lng": 67.0637},
      "timestamp": "2026-05-15T15:10:00Z",
      "credibility": 93,
      "likes": 2100,
      "retweets": 980,
      "verified": true
    },
    {
      "id": "P008",
      "source_type": "citizen",
      "platform": "Twitter",
      "username": "@karachimom",
      "text": "Korangi Industrial area mein factory mein aag lagi hai! Dhuan dekha ja raha hai Gulshan se bhi! #Karachi #Fire",
      "location": "Korangi Industrial Area",
      "coordinates": {"lat": 24.8269, "lng": 67.1228},
      "timestamp": "2026-05-15T11:12:00Z",
      "credibility": 65,
      "likes": 340,
      "retweets": 220,
      "verified": false
    },
    {
      "id": "P009",
      "source_type": "field_team",
      "platform": "CIRO Field App",
      "username": "FT-Korangi-02",
      "text": "Field report: Korangi paint factory fire confirmed. Wind direction NW — smoke heading toward Al-Falah Housing. Evacuation of 3 blocks recommended. Hazmat team needed.",
      "location": "Korangi Industrial Area",
      "coordinates": {"lat": 24.8268, "lng": 67.1230},
      "timestamp": "2026-05-15T11:55:00Z",
      "credibility": 97,
      "likes": 0,
      "retweets": 0,
      "verified": true
    },
    {
      "id": "P010",
      "source_type": "verified",
      "platform": "Twitter",
      "username": "@KarachiFireDept",
      "text": "Fire Brigade response: 4 fire tenders deployed to Korangi Industrial Area. Fire being brought under control. Civilians maintain 500m distance.",
      "location": "Korangi Industrial Area",
      "coordinates": {"lat": 24.8265, "lng": 67.1235},
      "timestamp": "2026-05-15T12:10:00Z",
      "credibility": 97,
      "likes": 650,
      "retweets": 890,
      "verified": true
    },
    {
      "id": "P011",
      "source_type": "citizen",
      "platform": "Twitter",
      "username": "@lyariwala",
      "text": "Lyari Expressway pe tanker ulat gaya hai Baloch Colony ke paas. Traffic jam hai 5km tak. Mat aao is taraf.",
      "location": "Lyari Expressway",
      "coordinates": {"lat": 24.8650, "lng": 66.9950},
      "timestamp": "2026-05-15T11:38:00Z",
      "credibility": 68,
      "likes": 290,
      "retweets": 175,
      "verified": false
    },
    {
      "id": "P012",
      "source_type": "news_outlet",
      "platform": "Dawn News",
      "username": "@dawn_urdu",
      "text": "Lyari Expressway accident: 3 tanker pile-up at Baloch Colony. 5 injured, 2 critical. Rescue 1122 on scene. Expressway closed in both directions.",
      "location": "Lyari Expressway",
      "coordinates": {"lat": 24.8648, "lng": 66.9948},
      "timestamp": "2026-05-15T11:50:00Z",
      "credibility": 92,
      "likes": 1800,
      "retweets": 1100,
      "verified": true
    },
    {
      "id": "P013",
      "source_type": "citizen",
      "platform": "Facebook",
      "username": "Rashid Karachi",
      "text": "Gulshan-e-Iqbal Block 10 mein barish se sab kuch bhar gaya. Flood aa gaya! Pani ghar mein ghus raha hai!",
      "location": "Gulshan-e-Iqbal",
      "coordinates": {"lat": 24.9218, "lng": 67.0921},
      "timestamp": "2026-05-15T09:08:00Z",
      "credibility": 55,
      "likes": 120,
      "retweets": 0,
      "verified": false
    },
    {
      "id": "P014",
      "source_type": "field_team",
      "platform": "CIRO Field App",
      "username": "FT-Gulshan-01",
      "text": "CORRECTION: Gulshan Block 10 — water main burst confirmed by KWSB. NOT monsoon flooding. Isolated incident. No danger to other areas. KWSB repair team deployed.",
      "location": "Gulshan-e-Iqbal",
      "coordinates": {"lat": 24.9218, "lng": 67.0921},
      "timestamp": "2026-05-15T09:48:00Z",
      "credibility": 98,
      "likes": 0,
      "retweets": 0,
      "verified": true
    },
    {
      "id": "P015",
      "source_type": "citizen",
      "platform": "Twitter",
      "username": "@site_worker",
      "text": "SITE mein bijli gayi 5 minute se zyada ho gaye. Factories band hone lagi hain. Hazar log sadak pe aa gaye. K-Electric kuch karo!",
      "location": "SITE Industrial Area",
      "coordinates": {"lat": 24.9120, "lng": 67.0050},
      "timestamp": "2026-05-15T17:33:00Z",
      "credibility": 65,
      "likes": 890,
      "retweets": 430,
      "verified": false
    },
    {
      "id": "P016",
      "source_type": "news_outlet",
      "platform": "The News",
      "username": "@TheNewsIntl",
      "text": "K-Electric grid failure hits SITE Industrial Area. 200+ factories affected. K-Electric estimates 3-4 hour restoration time. Worker safety concerns raised.",
      "location": "SITE Industrial Area",
      "coordinates": {"lat": 24.9118, "lng": 67.0048},
      "timestamp": "2026-05-15T17:45:00Z",
      "credibility": 91,
      "likes": 2300,
      "retweets": 1400,
      "verified": true
    },
    {
      "id": "P017",
      "source_type": "field_team",
      "platform": "CIRO Field App",
      "username": "FT-Malir-01",
      "text": "URGENT: Malir Road bridge section collapsed near Malir Halt. 2 motorcycles + 1 Suzuki van in ditch. 6 confirmed injured, 1 critical. Require 3 ambulances + rescue crane.",
      "location": "Malir Road",
      "coordinates": {"lat": 24.9000, "lng": 67.1800},
      "timestamp": "2026-05-15T17:42:00Z",
      "credibility": 98,
      "likes": 0,
      "retweets": 0,
      "verified": true
    },
    {
      "id": "P018",
      "source_type": "citizen",
      "platform": "WhatsApp (shared)",
      "username": "Unknown",
      "text": "Malir road bilkul theek hai. Main abhi se guzra hun. Koi accident nahi. Fake news hai.",
      "location": "Malir Road",
      "coordinates": {"lat": 24.9000, "lng": 67.1800},
      "timestamp": "2026-05-15T17:55:00Z",
      "credibility": 15,
      "likes": 0,
      "retweets": 0,
      "verified": false,
      "flag": "contradicts_field_team_high_credibility"
    },
    {
      "id": "P019",
      "source_type": "verified",
      "platform": "Twitter",
      "username": "@Rescue1122Khi",
      "text": "Rescue 1122 deployed to Malir Road collapse. 3 units on scene. Crane requested. Critical patient airlifted to Jinnah Hospital. Road closed indefinitely.",
      "location": "Malir Road",
      "coordinates": {"lat": 24.9000, "lng": 67.1800},
      "timestamp": "2026-05-15T18:05:00Z",
      "credibility": 97,
      "likes": 1100,
      "retweets": 780,
      "verified": true
    },
    {
      "id": "P020",
      "source_type": "citizen",
      "platform": "Twitter",
      "username": "@NorthKarachiResident",
      "text": "North Karachi mein 12 ghante se light nahi. Pani bhi nahi aa raha. Garmi mein bachay tadap rahe hain. Koi sunta hai? @KarachiMetro @PMO_Pakistan",
      "location": "North Karachi",
      "coordinates": {"lat": 24.9920, "lng": 67.0635},
      "timestamp": "2026-05-15T16:00:00Z",
      "credibility": 60,
      "likes": 560,
      "retweets": 320,
      "verified": false
    }
  ]
}
